setux/distros/debian.py
setux/distros/freebsd.py
setux_distros-0.2344.0.dist-info/METADATA
setux_distros-0.2344.0.dist-info/WHEEL
setux_distros-0.2344.0.dist-info/top_level.txt
setux_distros-0.2344.0.dist-info/RECORD
